include/fmt/args.h
include/fmt/base.h
include/fmt/chrono.h
include/fmt/color.h
include/fmt/compile.h
include/fmt/core.h
include/fmt/format-inl.h
include/fmt/format.h
include/fmt/os.h
include/fmt/ostream.h
include/fmt/printf.h
include/fmt/ranges.h
include/fmt/std.h
include/fmt/xchar.h
lib/cmake/fmt/fmt-config-version.cmake
lib/cmake/fmt/fmt-config.cmake
lib/cmake/fmt/fmt-targets-release.cmake
lib/cmake/fmt/fmt-targets.cmake
lib/fmt.lib
lib/pkgconfig/fmt.pc
rfmux/__init__.py
rfmux/_version.py
rfmux/algorithms/__init__.py
rfmux/algorithms/measurement/__init__.py
rfmux/algorithms/measurement/bias_kids.py
rfmux/algorithms/measurement/fitting.py
rfmux/algorithms/measurement/fitting_nonlinear.py
rfmux/algorithms/measurement/multisweep.py
rfmux/algorithms/measurement/py_get_pfb_samples.py
rfmux/algorithms/measurement/py_get_samples.py
rfmux/algorithms/measurement/take_netanal.py
rfmux/algorithms/README
rfmux/awaitless.py
rfmux/core/__init__.py
rfmux/core/crs.py
rfmux/core/dirfile.py
rfmux/core/hardware_map.py
rfmux/core/mock_config.py
rfmux/core/schema.py
rfmux/core/session.py
rfmux/core/transferfunctions.py
rfmux/mock/__init__.py
rfmux/mock/config.py
rfmux/mock/crs.py
rfmux/mock/helpers.py
rfmux/mock/README.md
rfmux/mock/resonator_model.py
rfmux/mock/server.py
rfmux/mock/udp_streamer.py
rfmux/mr_resonator/__init__.py
rfmux/mr_resonator/jit_physics.py
rfmux/mr_resonator/LICENSE
rfmux/mr_resonator/mr_complex_resonator.py
rfmux/mr_resonator/mr_lekid.py
rfmux/mr_resonator/utils.py
rfmux/streamer/.gitignore
rfmux/streamer/__init__.py
rfmux/streamer/_receiver.cp311-win32.pyd
rfmux/streamer/CMakeLists.txt
rfmux/streamer/include/packet.h
rfmux/streamer/include/packets.hpp
rfmux/streamer/include/tuber_support.hpp
rfmux/streamer/socket.py
rfmux/streamer/src/bindings.cpp
rfmux/streamer/src/packets.cpp
rfmux/tools/__init__.py
rfmux/tools/parser.py
rfmux/tools/periscope/__init__.py
rfmux/tools/periscope/__main__.py
rfmux/tools/periscope/app.py
rfmux/tools/periscope/app_runtime.py
rfmux-1.2.0rc1.dist-info/METADATA
rfmux-1.2.0rc1.dist-info/WHEEL
rfmux-1.2.0rc1.dist-info/entry_points.txt
rfmux-1.2.0rc1.dist-info/licenses/LICENSE
rfmux-1.2.0rc1.dist-info/RECORD
