Metadata-Version: 2.2
Name: rfmux
Version: 1.2.0rc1
Summary: Python library for t0.technology CRS board running rfmux firmware
Author-Email: Graeme Smecher <gsmecher@t0.technology>, Joshua Montgomery <joshua@t0.technology>
Project-URL: homepage, https://github.com/t0/rfmux
Project-URL: repository, https://github.com/t0/rfmux
Requires-Python: >=3.9
Requires-Dist: PyQt6
Requires-Dist: aiohttp
Requires-Dist: ipykernel<7
Requires-Dist: ipython
Requires-Dist: jupyterlab
Requires-Dist: matplotlib
Requires-Dist: numba
Requires-Dist: numpy
Requires-Dist: psutil
Requires-Dist: pyqtgraph
Requires-Dist: pytest
Requires-Dist: pytest-asyncio
Requires-Dist: pyyaml
Requires-Dist: qtconsole
Requires-Dist: requests_futures
Requires-Dist: scipy
Requires-Dist: simplejson
Requires-Dist: sqlalchemy
Requires-Dist: tbb; sys_platform != "darwin"
Provides-Extra: dirfile
